br_locations/__init__.py
br_locations/base.py
br_locations/states_and_cities_10_22.json
br_locations-0.1.0.dist-info/LICENSE
br_locations-0.1.0.dist-info/METADATA
br_locations-0.1.0.dist-info/WHEEL
br_locations-0.1.0.dist-info/top_level.txt
br_locations-0.1.0.dist-info/RECORD
